{
    "name": "Pancreas (by batch)",
    "headers": {
        "names": [
            "Rank",
            "Micro F1 score",
            "Accuracy",
            "F1 score",
            "Memory (GB)",
            "Runtime (min)",
            "CPU (%)",
            "Name",
            "Paper",
            "Code",
            "Year"
        ],
        "fixed": [
            "Name",
            "Paper",
            "Website",
            "Code"
        ]
    },
    "results": [
        {
            "Name": "K-neighbors classifier (log CPM)",
            "Paper": "Nearest neighbor pattern classification",
            "Paper URL": "https://doi.org/10.1109/TIT.1967.1053964",
            "Year": 1967,
            "Code": "https://scikit-learn.org/stable/modules/generated/sklearn.neighbors.KNeighborsClassifier.html",
            "Version": "1.0.2",
            "Runtime (min)": 6.566666666666666,
            "CPU (%)": 312.6,
            "Memory (GB)": 6.0,
            "Rank": 6,
            "Micro F1 score": 0.761157695428726,
            "Accuracy": 0.761157695428726,
            "F1 score": 0.7539271772245253
        },
        {
            "Name": "Logistic regression (log CPM)",
            "Paper": "Applied Logistic Regression",
            "Paper URL": "https://books.google.com/books?id=64JYAwAAQBAJ",
            "Year": 2013,
            "Code": "https://scikit-learn.org/stable/modules/generated/sklearn.linear_model.LogisticRegression.html",
            "Version": "1.0.2",
            "Runtime (min)": 7.116666666666666,
            "CPU (%)": 305.7,
            "Memory (GB)": 6.0,
            "Rank": 2,
            "Accuracy": 0.9550987286989451,
            "Micro F1 score": 0.9550987286989451,
            "F1 score": 0.9547494147051987
        },
        {
            "Name": "Multilayer perceptron (log CPM)",
            "Paper": "Connectionist learning procedures",
            "Paper URL": "https://www.sciencedirect.com/science/article/pii/B9780080510552500298",
            "Year": 1990,
            "Code": "https://scikit-learn.org/stable/modules/generated/sklearn.neural_network.MLPClassifier.html",
            "Version": "1.0.2",
            "Runtime (min)": 7.316666666666666,
            "CPU (%)": 391.0,
            "Memory (GB)": 6.0,
            "Rank": 1,
            "Micro F1 score": 0.967541249661888,
            "F1 score": 0.9681805961338414,
            "Accuracy": 0.967541249661888
        },
        {
            "Name": "K-neighbors classifier (log scran)",
            "Paper": "Nearest neighbor pattern classification",
            "Paper URL": "https://doi.org/10.1109/TIT.1967.1053964",
            "Year": 1967,
            "Code": "https://scikit-learn.org/stable/modules/generated/sklearn.neighbors.KNeighborsClassifier.html",
            "Version": "1.0.2",
            "Runtime (min)": 13.633333333333333,
            "CPU (%)": 152.0,
            "Memory (GB)": 19.0,
            "Rank": 5,
            "Accuracy": 0.8309440086556668,
            "F1 score": 0.8342036405746948,
            "Micro F1 score": 0.8309440086556668
        },
        {
            "Name": "Logistic regression (log scran)",
            "Paper": "Applied Logistic Regression",
            "Paper URL": "https://books.google.com/books?id=64JYAwAAQBAJ",
            "Year": 2013,
            "Code": "https://scikit-learn.org/stable/modules/generated/sklearn.linear_model.LogisticRegression.html",
            "Version": "1.0.2",
            "Runtime (min)": 13.966666666666667,
            "CPU (%)": 150.7,
            "Memory (GB)": 20.8,
            "Rank": 4,
            "Micro F1 score": 0.943467676494455,
            "F1 score": 0.9423066841275621,
            "Accuracy": 0.943467676494455
        },
        {
            "Name": "Multilayer perceptron (log scran)",
            "Paper": "Connectionist learning procedures",
            "Paper URL": "https://www.sciencedirect.com/science/article/pii/B9780080510552500298",
            "Year": 1990,
            "Code": "https://scikit-learn.org/stable/modules/generated/sklearn.neural_network.MLPClassifier.html",
            "Version": "1.0.2",
            "Runtime (min)": 13.966666666666667,
            "CPU (%)": 232.6,
            "Memory (GB)": 20.8,
            "Rank": 3,
            "Micro F1 score": 0.9499594265620773,
            "Accuracy": 0.9499594265620773,
            "F1 score": 0.9505828826000006
        }
    ]
}
